TSPsolver_fed/__init__.py
TSPsolver_fed/example_usage.py
TSPsolver_fed/utils.py
TSPsolver_fed/algorithms/Asearch.py
TSPsolver_fed/algorithms/__init__.py
TSPsolver_fed/algorithms/hill_climbing.py
TSPsolver_fed/algorithms/random_search.py
TSPsolver_fed/algorithms/simulated_annealing.py
tspsolver_fd9-0.1.0.dist-info/METADATA
tspsolver_fd9-0.1.0.dist-info/WHEEL
tspsolver_fd9-0.1.0.dist-info/top_level.txt
tspsolver_fd9-0.1.0.dist-info/RECORD
