Metadata-Version: 2.2
Name: TSPsolver_FD9
Version: 0.1.0
Summary: A library for solving the Traveling Salesman Problem using various algorithms.
Author-email: Frank <frank.dadzie@students.cau.edu>
Classifier: Programming Language :: Python :: 3
Classifier: Operating System :: OS Independent
Classifier: License :: OSI Approved :: MIT License
